{"nodes": [{"id": "linear", "label": "linear.py", "file_type": "code", "source_file": "refs/dinov3/dinov3/eval/linear.py", "source_location": "L1"}, {"id": "linear_optimizertype", "label": "OptimizerType", "file_type": "code", "source_file": "refs/dinov3/dinov3/eval/linear.py", "source_location": "L54"}, {"id": "enum", "label": "Enum", "file_type": "code", "source_file": "", "source_location": ""}, {"id": "linear_optimizertype_get_optimizer", "label": ".get_optimizer()", "file_type": "code", "source_file": "refs/dinov3/dinov3/eval/linear.py", "source_location": "L58"}, {"id": "linear_schedulertype", "label": "SchedulerType", "file_type": "code", "source_file": "refs/dinov3/dinov3/eval/linear.py", "source_location": "L66"}, {"id": "linear_schedulertype_get_scheduler", "label": ".get_scheduler()", "file_type": "code", "source_file": "refs/dinov3/dinov3/eval/linear.py", "source_location": "L70"}, {"id": "linear_trainconfig", "label": "TrainConfig", "file_type": "code", "source_file": "refs/dinov3/dinov3/eval/linear.py", "source_location": "L85"}, {"id": "linear_evalconfig", "label": "EvalConfig", "file_type": "code", "source_file": "refs/dinov3/dinov3/eval/linear.py", "source_location": "L109"}, {"id": "linear_transformconfig", "label": "TransformConfig", "file_type": "code", "source_file": "refs/dinov3/dinov3/eval/linear.py", "source_location": "L117"}, {"id": "linear_fewshotconfig", "label": "FewShotConfig", "file_type": "code", "source_file": "refs/dinov3/dinov3/eval/linear.py", "source_location": "L123"}, {"id": "linear_linearevalconfig", "label": "LinearEvalConfig", "file_type": "code", "source_file": "refs/dinov3/dinov3/eval/linear.py", "source_location": "L130"}, {"id": "linear_has_ddp_wrapper", "label": "has_ddp_wrapper()", "file_type": "code", "source_file": "refs/dinov3/dinov3/eval/linear.py", "source_location": "L140"}, {"id": "linear_remove_ddp_wrapper", "label": "remove_ddp_wrapper()", "file_type": "code", "source_file": "refs/dinov3/dinov3/eval/linear.py", "source_location": "L144"}, {"id": "linear_create_linear_input", "label": "create_linear_input()", "file_type": "code", "source_file": "refs/dinov3/dinov3/eval/linear.py", "source_location": "L148"}, {"id": "linear_linearclassifier", "label": "LinearClassifier", "file_type": "code", "source_file": "refs/dinov3/dinov3/eval/linear.py", "source_location": "L163"}, {"id": "linear_linearclassifier_init", "label": ".__init__()", "file_type": "code", "source_file": "refs/dinov3/dinov3/eval/linear.py", "source_location": "L166"}, {"id": "linear_linearclassifier_forward", "label": ".forward()", "file_type": "code", "source_file": "refs/dinov3/dinov3/eval/linear.py", "source_location": "L176"}, {"id": "linear_allclassifiers", "label": "AllClassifiers", "file_type": "code", "source_file": "refs/dinov3/dinov3/eval/linear.py", "source_location": "L181"}, {"id": "linear_allclassifiers_init", "label": ".__init__()", "file_type": "code", "source_file": "refs/dinov3/dinov3/eval/linear.py", "source_location": "L182"}, {"id": "linear_allclassifiers_forward", "label": ".forward()", "file_type": "code", "source_file": "refs/dinov3/dinov3/eval/linear.py", "source_location": "L187"}, {"id": "linear_allclassifiers_len", "label": ".__len__()", "file_type": "code", "source_file": "refs/dinov3/dinov3/eval/linear.py", "source_location": "L190"}, {"id": "linear_linearpostprocessor", "label": "LinearPostprocessor", "file_type": "code", "source_file": "refs/dinov3/dinov3/eval/linear.py", "source_location": "L194"}, {"id": "linear_linearpostprocessor_init", "label": ".__init__()", "file_type": "code", "source_file": "refs/dinov3/dinov3/eval/linear.py", "source_location": "L195"}, {"id": "linear_linearpostprocessor_forward", "label": ".forward()", "file_type": "code", "source_file": "refs/dinov3/dinov3/eval/linear.py", "source_location": "L200"}, {"id": "linear_scale_lr", "label": "scale_lr()", "file_type": "code", "source_file": "refs/dinov3/dinov3/eval/linear.py", "source_location": "L208"}, {"id": "linear_setup_linear_classifiers", "label": "setup_linear_classifiers()", "file_type": "code", "source_file": "refs/dinov3/dinov3/eval/linear.py", "source_location": "L212"}, {"id": "linear_make_eval_transform", "label": "make_eval_transform()", "file_type": "code", "source_file": "refs/dinov3/dinov3/eval/linear.py", "source_location": "L236"}, {"id": "linear_make_eval_data_loader", "label": "make_eval_data_loader()", "file_type": "code", "source_file": "refs/dinov3/dinov3/eval/linear.py", "source_location": "L245"}, {"id": "linear_evaluator", "label": "Evaluator", "file_type": "code", "source_file": "refs/dinov3/dinov3/eval/linear.py", "source_location": "L274"}, {"id": "linear_evaluator_post_init", "label": ".__post_init__()", "file_type": "code", "source_file": "refs/dinov3/dinov3/eval/linear.py", "source_location": "L284"}, {"id": "linear_evaluate_linear_classifiers", "label": "_evaluate_linear_classifiers()", "file_type": "code", "source_file": "refs/dinov3/dinov3/eval/linear.py", "source_location": "L295"}, {"id": "linear_evaluator_evaluate_and_maybe_save", "label": ".evaluate_and_maybe_save()", "file_type": "code", "source_file": "refs/dinov3/dinov3/eval/linear.py", "source_location": "L352"}, {"id": "linear_make_evaluators", "label": "make_evaluators()", "file_type": "code", "source_file": "refs/dinov3/dinov3/eval/linear.py", "source_location": "L383"}, {"id": "linear_setup_linear_training", "label": "setup_linear_training()", "file_type": "code", "source_file": "refs/dinov3/dinov3/eval/linear.py", "source_location": "L416"}, {"id": "linear_train_linear_classifiers", "label": "train_linear_classifiers()", "file_type": "code", "source_file": "refs/dinov3/dinov3/eval/linear.py", "source_location": "L467"}, {"id": "linear_make_train_transform", "label": "make_train_transform()", "file_type": "code", "source_file": "refs/dinov3/dinov3/eval/linear.py", "source_location": "L577"}, {"id": "linear_make_train_dataset", "label": "make_train_dataset()", "file_type": "code", "source_file": "refs/dinov3/dinov3/eval/linear.py", "source_location": "L582"}, {"id": "linear_eval_linear_with_model", "label": "eval_linear_with_model()", "file_type": "code", "source_file": "refs/dinov3/dinov3/eval/linear.py", "source_location": "L587"}, {"id": "linear_benchmark_launcher", "label": "benchmark_launcher()", "file_type": "code", "source_file": "refs/dinov3/dinov3/eval/linear.py", "source_location": "L667"}, {"id": "linear_main", "label": "main()", "file_type": "code", "source_file": "refs/dinov3/dinov3/eval/linear.py", "source_location": "L678"}, {"id": "linear_rationale_164", "label": "Linear layer to train on top of frozen features", "file_type": "rationale", "source_file": "refs/dinov3/dinov3/eval/linear.py", "source_location": "L164"}, {"id": "linear_rationale_668", "label": "Initialization of distributed and logging are preconditions for this method", "file_type": "rationale", "source_file": "refs/dinov3/dinov3/eval/linear.py", "source_location": "L668"}], "edges": [{"source": "linear", "target": "json", "relation": "imports", "confidence": "EXTRACTED", "source_file": "refs/dinov3/dinov3/eval/linear.py", "source_location": "L6", "weight": 1.0}, {"source": "linear", "target": "logging", "relation": "imports", "confidence": "EXTRACTED", "source_file": "refs/dinov3/dinov3/eval/linear.py", "source_location": "L7", "weight": 1.0}, {"source": "linear", "target": "os", "relation": "imports", "confidence": "EXTRACTED", "source_file": "refs/dinov3/dinov3/eval/linear.py", "source_location": "L8", "weight": 1.0}, {"source": "linear", "target": "sys", "relation": "imports", "confidence": "EXTRACTED", "source_file": "refs/dinov3/dinov3/eval/linear.py", "source_location": "L9", "weight": 1.0}, {"source": "linear", "target": "time", "relation": "imports", "confidence": "EXTRACTED", "source_file": "refs/dinov3/dinov3/eval/linear.py", "source_location": "L10", "weight": 1.0}, {"source": "linear", "target": "dataclasses", "relation": "imports_from", "confidence": "EXTRACTED", "source_file": "refs/dinov3/dinov3/eval/linear.py", "source_location": "L11", "weight": 1.0}, {"source": "linear", "target": "enum", "relation": "imports_from", "confidence": "EXTRACTED", "source_file": "refs/dinov3/dinov3/eval/linear.py", "source_location": "L12", "weight": 1.0}, {"source": "linear", "target": "functools", "relation": "imports_from", "confidence": "EXTRACTED", "source_file": "refs/dinov3/dinov3/eval/linear.py", "source_location": "L13", "weight": 1.0}, {"source": "linear", "target": "pathlib", "relation": "imports_from", "confidence": "EXTRACTED", "source_file": "refs/dinov3/dinov3/eval/linear.py", "source_location": "L14", "weight": 1.0}, {"source": "linear", "target": "typing", "relation": "imports_from", "confidence": "EXTRACTED", "source_file": "refs/dinov3/dinov3/eval/linear.py", "source_location": "L15", "weight": 1.0}, {"source": "linear", "target": "torch", "relation": "imports", "confidence": "EXTRACTED", "source_file": "refs/dinov3/dinov3/eval/linear.py", "source_location": "L17", "weight": 1.0}, {"source": "linear", "target": "torch_backends_cudnn", "relation": "imports", "confidence": "EXTRACTED", "source_file": "refs/dinov3/dinov3/eval/linear.py", "source_location": "L18", "weight": 1.0}, {"source": "linear", "target": "torch_nn", "relation": "imports", "confidence": "EXTRACTED", "source_file": "refs/dinov3/dinov3/eval/linear.py", "source_location": "L19", "weight": 1.0}, {"source": "linear", "target": "omegaconf", "relation": "imports_from", "confidence": "EXTRACTED", "source_file": "refs/dinov3/dinov3/eval/linear.py", "source_location": "L20", "weight": 1.0}, {"source": "linear", "target": "torch_nn_parallel", "relation": "imports_from", "confidence": "EXTRACTED", "source_file": "refs/dinov3/dinov3/eval/linear.py", "source_location": "L21", "weight": 1.0}, {"source": "linear", "target": "dinov3_distributed", "relation": "imports", "confidence": "EXTRACTED", "source_file": "refs/dinov3/dinov3/eval/linear.py", "source_location": "L23", "weight": 1.0}, {"source": "linear", "target": "dinov3_checkpointer", "relation": "imports_from", "confidence": "EXTRACTED", "source_file": "refs/dinov3/dinov3/eval/linear.py", "source_location": "L24", "weight": 1.0}, {"source": "linear", "target": "dinov3_data", "relation": "imports_from", "confidence": "EXTRACTED", "source_file": "refs/dinov3/dinov3/eval/linear.py", "source_location": "L30", "weight": 1.0}, {"source": "linear", "target": "dinov3_data_adapters", "relation": "imports_from", "confidence": "EXTRACTED", "source_file": "refs/dinov3/dinov3/eval/linear.py", "source_location": "L31", "weight": 1.0}, {"source": "linear", "target": "dinov3_data_transforms", "relation": "imports_from", "confidence": "EXTRACTED", "source_file": "refs/dinov3/dinov3/eval/linear.py", "source_location": "L32", "weight": 1.0}, {"source": "linear", "target": "dinov3_eval_data", "relation": "imports_from", "confidence": "EXTRACTED", "source_file": "refs/dinov3/dinov3/eval/linear.py", "source_location": "L38", "weight": 1.0}, {"source": "linear", "target": "dinov3_eval_helpers", "relation": "imports_from", "confidence": "EXTRACTED", "source_file": "refs/dinov3/dinov3/eval/linear.py", "source_location": "L39", "weight": 1.0}, {"source": "linear", "target": "dinov3_eval_metrics", "relation": "imports_from", "confidence": "EXTRACTED", "source_file": "refs/dinov3/dinov3/eval/linear.py", "source_location": "L40", "weight": 1.0}, {"source": "linear", "target": "dinov3_eval_setup", "relation": "imports_from", "confidence": "EXTRACTED", "source_file": "refs/dinov3/dinov3/eval/linear.py", "source_location": "L41", "weight": 1.0}, {"source": "linear", "target": "dinov3_eval_utils", "relation": "imports_from", "confidence": "EXTRACTED", "source_file": "refs/dinov3/dinov3/eval/linear.py", "source_location": "L42", "weight": 1.0}, {"source": "linear", "target": "dinov3_eval_utils", "relation": "imports_from", "confidence": "EXTRACTED", "source_file": "refs/dinov3/dinov3/eval/linear.py", "source_location": "L43", "weight": 1.0}, {"source": "linear", "target": "dinov3_logging", "relation": "imports_from", "confidence": "EXTRACTED", "source_file": "refs/dinov3/dinov3/eval/linear.py", "source_location": "L44", "weight": 1.0}, {"source": "linear", "target": "dinov3_run_init", "relation": "imports_from", "confidence": "EXTRACTED", "source_file": "refs/dinov3/dinov3/eval/linear.py", "source_location": "L45", "weight": 1.0}, {"source": "linear", "target": "linear_optimizertype", "relation": "contains", "confidence": "EXTRACTED", "source_file": "refs/dinov3/dinov3/eval/linear.py", "source_location": "L54", "weight": 1.0}, {"source": "linear_optimizertype", "target": "enum", "relation": "inherits", "confidence": "EXTRACTED", "source_file": "refs/dinov3/dinov3/eval/linear.py", "source_location": "L54", "weight": 1.0}, {"source": "linear_optimizertype", "target": "linear_optimizertype_get_optimizer", "relation": "method", "confidence": "EXTRACTED", "source_file": "refs/dinov3/dinov3/eval/linear.py", "source_location": "L58", "weight": 1.0}, {"source": "linear", "target": "linear_schedulertype", "relation": "contains", "confidence": "EXTRACTED", "source_file": "refs/dinov3/dinov3/eval/linear.py", "source_location": "L66", "weight": 1.0}, {"source": "linear_schedulertype", "target": "enum", "relation": "inherits", "confidence": "EXTRACTED", "source_file": "refs/dinov3/dinov3/eval/linear.py", "source_location": "L66", "weight": 1.0}, {"source": "linear_schedulertype", "target": "linear_schedulertype_get_scheduler", "relation": "method", "confidence": "EXTRACTED", "source_file": "refs/dinov3/dinov3/eval/linear.py", "source_location": "L70", "weight": 1.0}, {"source": "linear", "target": "linear_trainconfig", "relation": "contains", "confidence": "EXTRACTED", "source_file": "refs/dinov3/dinov3/eval/linear.py", "source_location": "L85", "weight": 1.0}, {"source": "linear", "target": "linear_evalconfig", "relation": "contains", "confidence": "EXTRACTED", "source_file": "refs/dinov3/dinov3/eval/linear.py", "source_location": "L109", "weight": 1.0}, {"source": "linear", "target": "linear_transformconfig", "relation": "contains", "confidence": "EXTRACTED", "source_file": "refs/dinov3/dinov3/eval/linear.py", "source_location": "L117", "weight": 1.0}, {"source": "linear", "target": "linear_fewshotconfig", "relation": "contains", "confidence": "EXTRACTED", "source_file": "refs/dinov3/dinov3/eval/linear.py", "source_location": "L123", "weight": 1.0}, {"source": "linear", "target": "linear_linearevalconfig", "relation": "contains", "confidence": "EXTRACTED", "source_file": "refs/dinov3/dinov3/eval/linear.py", "source_location": "L130", "weight": 1.0}, {"source": "linear", "target": "linear_has_ddp_wrapper", "relation": "contains", "confidence": "EXTRACTED", "source_file": "refs/dinov3/dinov3/eval/linear.py", "source_location": "L140", "weight": 1.0}, {"source": "linear", "target": "linear_remove_ddp_wrapper", "relation": "contains", "confidence": "EXTRACTED", "source_file": "refs/dinov3/dinov3/eval/linear.py", "source_location": "L144", "weight": 1.0}, {"source": "linear", "target": "linear_create_linear_input", "relation": "contains", "confidence": "EXTRACTED", "source_file": "refs/dinov3/dinov3/eval/linear.py", "source_location": "L148", "weight": 1.0}, {"source": "linear", "target": "linear_linearclassifier", "relation": "contains", "confidence": "EXTRACTED", "source_file": "refs/dinov3/dinov3/eval/linear.py", "source_location": "L163", "weight": 1.0}, {"source": "linear_linearclassifier", "target": "linear_linearclassifier_init", "relation": "method", "confidence": "EXTRACTED", "source_file": "refs/dinov3/dinov3/eval/linear.py", "source_location": "L166", "weight": 1.0}, {"source": "linear_linearclassifier", "target": "linear_linearclassifier_forward", "relation": "method", "confidence": "EXTRACTED", "source_file": "refs/dinov3/dinov3/eval/linear.py", "source_location": "L176", "weight": 1.0}, {"source": "linear", "target": "linear_allclassifiers", "relation": "contains", "confidence": "EXTRACTED", "source_file": "refs/dinov3/dinov3/eval/linear.py", "source_location": "L181", "weight": 1.0}, {"source": "linear_allclassifiers", "target": "linear_allclassifiers_init", "relation": "method", "confidence": "EXTRACTED", "source_file": "refs/dinov3/dinov3/eval/linear.py", "source_location": "L182", "weight": 1.0}, {"source": "linear_allclassifiers", "target": "linear_allclassifiers_forward", "relation": "method", "confidence": "EXTRACTED", "source_file": "refs/dinov3/dinov3/eval/linear.py", "source_location": "L187", "weight": 1.0}, {"source": "linear_allclassifiers", "target": "linear_allclassifiers_len", "relation": "method", "confidence": "EXTRACTED", "source_file": "refs/dinov3/dinov3/eval/linear.py", "source_location": "L190", "weight": 1.0}, {"source": "linear", "target": "linear_linearpostprocessor", "relation": "contains", "confidence": "EXTRACTED", "source_file": "refs/dinov3/dinov3/eval/linear.py", "source_location": "L194", "weight": 1.0}, {"source": "linear_linearpostprocessor", "target": "linear_linearpostprocessor_init", "relation": "method", "confidence": "EXTRACTED", "source_file": "refs/dinov3/dinov3/eval/linear.py", "source_location": "L195", "weight": 1.0}, {"source": "linear_linearpostprocessor", "target": "linear_linearpostprocessor_forward", "relation": "method", "confidence": "EXTRACTED", "source_file": "refs/dinov3/dinov3/eval/linear.py", "source_location": "L200", "weight": 1.0}, {"source": "linear", "target": "linear_scale_lr", "relation": "contains", "confidence": "EXTRACTED", "source_file": "refs/dinov3/dinov3/eval/linear.py", "source_location": "L208", "weight": 1.0}, {"source": "linear", "target": "linear_setup_linear_classifiers", "relation": "contains", "confidence": "EXTRACTED", "source_file": "refs/dinov3/dinov3/eval/linear.py", "source_location": "L212", "weight": 1.0}, {"source": "linear", "target": "linear_make_eval_transform", "relation": "contains", "confidence": "EXTRACTED", "source_file": "refs/dinov3/dinov3/eval/linear.py", "source_location": "L236", "weight": 1.0}, {"source": "linear", "target": "linear_make_eval_data_loader", "relation": "contains", "confidence": "EXTRACTED", "source_file": "refs/dinov3/dinov3/eval/linear.py", "source_location": "L245", "weight": 1.0}, {"source": "linear", "target": "linear_evaluator", "relation": "contains", "confidence": "EXTRACTED", "source_file": "refs/dinov3/dinov3/eval/linear.py", "source_location": "L274", "weight": 1.0}, {"source": "linear_evaluator", "target": "linear_evaluator_post_init", "relation": "method", "confidence": "EXTRACTED", "source_file": "refs/dinov3/dinov3/eval/linear.py", "source_location": "L284", "weight": 1.0}, {"source": "linear", "target": "linear_evaluate_linear_classifiers", "relation": "contains", "confidence": "EXTRACTED", "source_file": "refs/dinov3/dinov3/eval/linear.py", "source_location": "L295", "weight": 1.0}, {"source": "linear_evaluator", "target": "linear_evaluator_evaluate_and_maybe_save", "relation": "method", "confidence": "EXTRACTED", "source_file": "refs/dinov3/dinov3/eval/linear.py", "source_location": "L352", "weight": 1.0}, {"source": "linear", "target": "linear_make_evaluators", "relation": "contains", "confidence": "EXTRACTED", "source_file": "refs/dinov3/dinov3/eval/linear.py", "source_location": "L383", "weight": 1.0}, {"source": "linear", "target": "linear_setup_linear_training", "relation": "contains", "confidence": "EXTRACTED", "source_file": "refs/dinov3/dinov3/eval/linear.py", "source_location": "L416", "weight": 1.0}, {"source": "linear", "target": "linear_train_linear_classifiers", "relation": "contains", "confidence": "EXTRACTED", "source_file": "refs/dinov3/dinov3/eval/linear.py", "source_location": "L467", "weight": 1.0}, {"source": "linear", "target": "linear_make_train_transform", "relation": "contains", "confidence": "EXTRACTED", "source_file": "refs/dinov3/dinov3/eval/linear.py", "source_location": "L577", "weight": 1.0}, {"source": "linear", "target": "linear_make_train_dataset", "relation": "contains", "confidence": "EXTRACTED", "source_file": "refs/dinov3/dinov3/eval/linear.py", "source_location": "L582", "weight": 1.0}, {"source": "linear", "target": "linear_eval_linear_with_model", "relation": "contains", "confidence": "EXTRACTED", "source_file": "refs/dinov3/dinov3/eval/linear.py", "source_location": "L587", "weight": 1.0}, {"source": "linear", "target": "linear_benchmark_launcher", "relation": "contains", "confidence": "EXTRACTED", "source_file": "refs/dinov3/dinov3/eval/linear.py", "source_location": "L667", "weight": 1.0}, {"source": "linear", "target": "linear_main", "relation": "contains", "confidence": "EXTRACTED", "source_file": "refs/dinov3/dinov3/eval/linear.py", "source_location": "L678", "weight": 1.0}, {"source": "linear_remove_ddp_wrapper", "target": "linear_has_ddp_wrapper", "relation": "calls", "confidence": "EXTRACTED", "source_file": "refs/dinov3/dinov3/eval/linear.py", "source_location": "L145", "weight": 1.0}, {"source": "linear_linearclassifier_init", "target": "linear_linearpostprocessor_init", "relation": "calls", "confidence": "EXTRACTED", "source_file": "refs/dinov3/dinov3/eval/linear.py", "source_location": "L167", "weight": 1.0}, {"source": "linear_linearclassifier_forward", "target": "linear_create_linear_input", "relation": "calls", "confidence": "EXTRACTED", "source_file": "refs/dinov3/dinov3/eval/linear.py", "source_location": "L177", "weight": 1.0}, {"source": "linear_allclassifiers_init", "target": "linear_linearpostprocessor_init", "relation": "calls", "confidence": "EXTRACTED", "source_file": "refs/dinov3/dinov3/eval/linear.py", "source_location": "L183", "weight": 1.0}, {"source": "linear_allclassifiers_forward", "target": "linear_linearpostprocessor_forward", "relation": "calls", "confidence": "EXTRACTED", "source_file": "refs/dinov3/dinov3/eval/linear.py", "source_location": "L188", "weight": 1.0}, {"source": "linear_setup_linear_classifiers", "target": "linear_scale_lr", "relation": "calls", "confidence": "EXTRACTED", "source_file": "refs/dinov3/dinov3/eval/linear.py", "source_location": "L218", "weight": 1.0}, {"source": "linear_setup_linear_classifiers", "target": "linear_create_linear_input", "relation": "calls", "confidence": "EXTRACTED", "source_file": "refs/dinov3/dinov3/eval/linear.py", "source_location": "L219", "weight": 1.0}, {"source": "linear_setup_linear_classifiers", "target": "linear_linearclassifier", "relation": "calls", "confidence": "EXTRACTED", "source_file": "refs/dinov3/dinov3/eval/linear.py", "source_location": "L220", "weight": 1.0}, {"source": "linear_setup_linear_classifiers", "target": "linear_allclassifiers", "relation": "calls", "confidence": "EXTRACTED", "source_file": "refs/dinov3/dinov3/eval/linear.py", "source_location": "L229", "weight": 1.0}, {"source": "linear_make_eval_data_loader", "target": "linear_make_eval_transform", "relation": "calls", "confidence": "EXTRACTED", "source_file": "refs/dinov3/dinov3/eval/linear.py", "source_location": "L253", "weight": 1.0}, {"source": "linear_evaluator_post_init", "target": "linear_make_eval_data_loader", "relation": "calls", "confidence": "EXTRACTED", "source_file": "refs/dinov3/dinov3/eval/linear.py", "source_location": "L285", "weight": 1.0}, {"source": "linear_evaluate_linear_classifiers", "target": "linear_linearpostprocessor", "relation": "calls", "confidence": "EXTRACTED", "source_file": "refs/dinov3/dinov3/eval/linear.py", "source_location": "L310", "weight": 1.0}, {"source": "linear_evaluator_evaluate_and_maybe_save", "target": "linear_evaluate_linear_classifiers", "relation": "calls", "confidence": "EXTRACTED", "source_file": "refs/dinov3/dinov3/eval/linear.py", "source_location": "L363", "weight": 1.0}, {"source": "linear_evaluator_evaluate_and_maybe_save", "target": "linear_remove_ddp_wrapper", "relation": "calls", "confidence": "EXTRACTED", "source_file": "refs/dinov3/dinov3/eval/linear.py", "source_location": "L365", "weight": 1.0}, {"source": "linear_make_evaluators", "target": "linear_evaluator", "relation": "calls", "confidence": "EXTRACTED", "source_file": "refs/dinov3/dinov3/eval/linear.py", "source_location": "L398", "weight": 1.0}, {"source": "linear_setup_linear_training", "target": "linear_setup_linear_classifiers", "relation": "calls", "confidence": "EXTRACTED", "source_file": "refs/dinov3/dinov3/eval/linear.py", "source_location": "L423", "weight": 1.0}, {"source": "linear_setup_linear_training", "target": "linear_optimizertype_get_optimizer", "relation": "calls", "confidence": "EXTRACTED", "source_file": "refs/dinov3/dinov3/eval/linear.py", "source_location": "L431", "weight": 1.0}, {"source": "linear_setup_linear_training", "target": "linear_schedulertype_get_scheduler", "relation": "calls", "confidence": "EXTRACTED", "source_file": "refs/dinov3/dinov3/eval/linear.py", "source_location": "L432", "weight": 1.0}, {"source": "linear_train_linear_classifiers", "target": "linear_setup_linear_training", "relation": "calls", "confidence": "EXTRACTED", "source_file": "refs/dinov3/dinov3/eval/linear.py", "source_location": "L476", "weight": 1.0}, {"source": "linear_train_linear_classifiers", "target": "linear_evaluator_evaluate_and_maybe_save", "relation": "calls", "confidence": "EXTRACTED", "source_file": "refs/dinov3/dinov3/eval/linear.py", "source_location": "L553", "weight": 1.0}, {"source": "linear_make_train_dataset", "target": "linear_make_train_transform", "relation": "calls", "confidence": "EXTRACTED", "source_file": "refs/dinov3/dinov3/eval/linear.py", "source_location": "L583", "weight": 1.0}, {"source": "linear_eval_linear_with_model", "target": "linear_make_train_dataset", "relation": "calls", "confidence": "EXTRACTED", "source_file": "refs/dinov3/dinov3/eval/linear.py", "source_location": "L591", "weight": 1.0}, {"source": "linear_eval_linear_with_model", "target": "linear_make_evaluators", "relation": "calls", "confidence": "EXTRACTED", "source_file": "refs/dinov3/dinov3/eval/linear.py", "source_location": "L608", "weight": 1.0}, {"source": "linear_eval_linear_with_model", "target": "linear_train_linear_classifiers", "relation": "calls", "confidence": "EXTRACTED", "source_file": "refs/dinov3/dinov3/eval/linear.py", "source_location": "L628", "weight": 1.0}, {"source": "linear_eval_linear_with_model", "target": "linear_evaluator_evaluate_and_maybe_save", "relation": "calls", "confidence": "EXTRACTED", "source_file": "refs/dinov3/dinov3/eval/linear.py", "source_location": "L637", "weight": 1.0}, {"source": "linear_benchmark_launcher", "target": "linear_eval_linear_with_model", "relation": "calls", "confidence": "EXTRACTED", "source_file": "refs/dinov3/dinov3/eval/linear.py", "source_location": "L671", "weight": 1.0}, {"source": "linear_main", "target": "linear_benchmark_launcher", "relation": "calls", "confidence": "EXTRACTED", "source_file": "refs/dinov3/dinov3/eval/linear.py", "source_location": "L683", "weight": 1.0}, {"source": "linear_rationale_164", "target": "linear_linearclassifier", "relation": "rationale_for", "confidence": "EXTRACTED", "source_file": "refs/dinov3/dinov3/eval/linear.py", "source_location": "L164", "weight": 1.0}, {"source": "linear_rationale_668", "target": "linear_benchmark_launcher", "relation": "rationale_for", "confidence": "EXTRACTED", "source_file": "refs/dinov3/dinov3/eval/linear.py", "source_location": "L668", "weight": 1.0}]}