{"nodes": [{"id": "model_io", "label": "model_io.py", "file_type": "code", "source_file": "refs/zoedepth/zoedepth/models/model_io.py", "source_location": "L1"}, {"id": "model_io_load_state_dict", "label": "load_state_dict()", "file_type": "code", "source_file": "refs/zoedepth/zoedepth/models/model_io.py", "source_location": "L27"}, {"id": "model_io_load_wts", "label": "load_wts()", "file_type": "code", "source_file": "refs/zoedepth/zoedepth/models/model_io.py", "source_location": "L54"}, {"id": "model_io_load_state_dict_from_url", "label": "load_state_dict_from_url()", "file_type": "code", "source_file": "refs/zoedepth/zoedepth/models/model_io.py", "source_location": "L59"}, {"id": "model_io_load_state_from_resource", "label": "load_state_from_resource()", "file_type": "code", "source_file": "refs/zoedepth/zoedepth/models/model_io.py", "source_location": "L64"}, {"id": "model_io_rationale_28", "label": "Load state_dict into model, handling DataParallel and DistributedDataParallel. A", "file_type": "rationale", "source_file": "refs/zoedepth/zoedepth/models/model_io.py", "source_location": "L28"}, {"id": "model_io_rationale_65", "label": "Loads weights to the model from a given resource. A resource can be of following", "file_type": "rationale", "source_file": "refs/zoedepth/zoedepth/models/model_io.py", "source_location": "L65"}], "edges": [{"source": "model_io", "target": "torch", "relation": "imports", "confidence": "EXTRACTED", "source_file": "refs/zoedepth/zoedepth/models/model_io.py", "source_location": "L25", "weight": 1.0}, {"source": "model_io", "target": "model_io_load_state_dict", "relation": "contains", "confidence": "EXTRACTED", "source_file": "refs/zoedepth/zoedepth/models/model_io.py", "source_location": "L27", "weight": 1.0}, {"source": "model_io", "target": "model_io_load_wts", "relation": "contains", "confidence": "EXTRACTED", "source_file": "refs/zoedepth/zoedepth/models/model_io.py", "source_location": "L54", "weight": 1.0}, {"source": "model_io", "target": "model_io_load_state_dict_from_url", "relation": "contains", "confidence": "EXTRACTED", "source_file": "refs/zoedepth/zoedepth/models/model_io.py", "source_location": "L59", "weight": 1.0}, {"source": "model_io", "target": "model_io_load_state_from_resource", "relation": "contains", "confidence": "EXTRACTED", "source_file": "refs/zoedepth/zoedepth/models/model_io.py", "source_location": "L64", "weight": 1.0}, {"source": "model_io_load_wts", "target": "model_io_load_state_dict", "relation": "calls", "confidence": "EXTRACTED", "source_file": "refs/zoedepth/zoedepth/models/model_io.py", "source_location": "L56", "weight": 1.0}, {"source": "model_io_load_state_dict_from_url", "target": "model_io_load_state_dict", "relation": "calls", "confidence": "EXTRACTED", "source_file": "refs/zoedepth/zoedepth/models/model_io.py", "source_location": "L61", "weight": 1.0}, {"source": "model_io_load_state_from_resource", "target": "model_io_load_state_dict_from_url", "relation": "calls", "confidence": "EXTRACTED", "source_file": "refs/zoedepth/zoedepth/models/model_io.py", "source_location": "L84", "weight": 1.0}, {"source": "model_io_load_state_from_resource", "target": "model_io_load_wts", "relation": "calls", "confidence": "EXTRACTED", "source_file": "refs/zoedepth/zoedepth/models/model_io.py", "source_location": "L88", "weight": 1.0}, {"source": "model_io_rationale_28", "target": "model_io_load_state_dict", "relation": "rationale_for", "confidence": "EXTRACTED", "source_file": "refs/zoedepth/zoedepth/models/model_io.py", "source_location": "L28", "weight": 1.0}, {"source": "model_io_rationale_65", "target": "model_io_load_state_from_resource", "relation": "rationale_for", "confidence": "EXTRACTED", "source_file": "refs/zoedepth/zoedepth/models/model_io.py", "source_location": "L65", "weight": 1.0}]}