{"nodes": [{"id": "apgdt", "label": "apgdt.py", "file_type": "code", "source_file": "refs/adversarial_depth/torchattacks/attacks/apgdt.py", "source_location": "L1"}, {"id": "apgdt_apgdt", "label": "APGDT", "file_type": "code", "source_file": "refs/adversarial_depth/torchattacks/attacks/apgdt.py", "source_location": "L10"}, {"id": "attack", "label": "Attack", "file_type": "code", "source_file": "", "source_location": ""}, {"id": "apgdt_apgdt_init", "label": ".__init__()", "file_type": "code", "source_file": "refs/adversarial_depth/torchattacks/attacks/apgdt.py", "source_location": "L41"}, {"id": "apgdt_apgdt_forward", "label": ".forward()", "file_type": "code", "source_file": "refs/adversarial_depth/torchattacks/attacks/apgdt.py", "source_location": "L56"}, {"id": "apgdt_apgdt_check_oscillation", "label": ".check_oscillation()", "file_type": "code", "source_file": "refs/adversarial_depth/torchattacks/attacks/apgdt.py", "source_location": "L66"}, {"id": "apgdt_apgdt_check_shape", "label": ".check_shape()", "file_type": "code", "source_file": "refs/adversarial_depth/torchattacks/attacks/apgdt.py", "source_location": "L73"}, {"id": "apgdt_apgdt_dlr_loss_targeted", "label": ".dlr_loss_targeted()", "file_type": "code", "source_file": "refs/adversarial_depth/torchattacks/attacks/apgdt.py", "source_location": "L76"}, {"id": "apgdt_apgdt_attack_single_run", "label": ".attack_single_run()", "file_type": "code", "source_file": "refs/adversarial_depth/torchattacks/attacks/apgdt.py", "source_location": "L81"}, {"id": "apgdt_apgdt_perturb", "label": ".perturb()", "file_type": "code", "source_file": "refs/adversarial_depth/torchattacks/attacks/apgdt.py", "source_location": "L210"}, {"id": "apgdt_rationale_11", "label": "r\"\"\"     APGD-Targeted in the paper 'Reliable evaluation of adversarial robustne", "file_type": "rationale", "source_file": "refs/adversarial_depth/torchattacks/attacks/apgdt.py", "source_location": "L11"}, {"id": "apgdt_rationale_57", "label": "r\"\"\"         Overridden.", "file_type": "rationale", "source_file": "refs/adversarial_depth/torchattacks/attacks/apgdt.py", "source_location": "L57"}], "edges": [{"source": "apgdt", "target": "time", "relation": "imports", "confidence": "EXTRACTED", "source_file": "refs/adversarial_depth/torchattacks/attacks/apgdt.py", "source_location": "L1", "weight": 1.0}, {"source": "apgdt", "target": "numpy", "relation": "imports", "confidence": "EXTRACTED", "source_file": "refs/adversarial_depth/torchattacks/attacks/apgdt.py", "source_location": "L3", "weight": 1.0}, {"source": "apgdt", "target": "torch", "relation": "imports", "confidence": "EXTRACTED", "source_file": "refs/adversarial_depth/torchattacks/attacks/apgdt.py", "source_location": "L5", "weight": 1.0}, {"source": "apgdt", "target": "attack", "relation": "imports_from", "confidence": "EXTRACTED", "source_file": "refs/adversarial_depth/torchattacks/attacks/apgdt.py", "source_location": "L7", "weight": 1.0}, {"source": "apgdt", "target": "apgdt_apgdt", "relation": "contains", "confidence": "EXTRACTED", "source_file": "refs/adversarial_depth/torchattacks/attacks/apgdt.py", "source_location": "L10", "weight": 1.0}, {"source": "apgdt_apgdt", "target": "attack", "relation": "inherits", "confidence": "EXTRACTED", "source_file": "refs/adversarial_depth/torchattacks/attacks/apgdt.py", "source_location": "L10", "weight": 1.0}, {"source": "apgdt_apgdt", "target": "apgdt_apgdt_init", "relation": "method", "confidence": "EXTRACTED", "source_file": "refs/adversarial_depth/torchattacks/attacks/apgdt.py", "source_location": "L41", "weight": 1.0}, {"source": "apgdt_apgdt", "target": "apgdt_apgdt_forward", "relation": "method", "confidence": "EXTRACTED", "source_file": "refs/adversarial_depth/torchattacks/attacks/apgdt.py", "source_location": "L56", "weight": 1.0}, {"source": "apgdt_apgdt", "target": "apgdt_apgdt_check_oscillation", "relation": "method", "confidence": "EXTRACTED", "source_file": "refs/adversarial_depth/torchattacks/attacks/apgdt.py", "source_location": "L66", "weight": 1.0}, {"source": "apgdt_apgdt", "target": "apgdt_apgdt_check_shape", "relation": "method", "confidence": "EXTRACTED", "source_file": "refs/adversarial_depth/torchattacks/attacks/apgdt.py", "source_location": "L73", "weight": 1.0}, {"source": "apgdt_apgdt", "target": "apgdt_apgdt_dlr_loss_targeted", "relation": "method", "confidence": "EXTRACTED", "source_file": "refs/adversarial_depth/torchattacks/attacks/apgdt.py", "source_location": "L76", "weight": 1.0}, {"source": "apgdt_apgdt", "target": "apgdt_apgdt_attack_single_run", "relation": "method", "confidence": "EXTRACTED", "source_file": "refs/adversarial_depth/torchattacks/attacks/apgdt.py", "source_location": "L81", "weight": 1.0}, {"source": "apgdt_apgdt", "target": "apgdt_apgdt_perturb", "relation": "method", "confidence": "EXTRACTED", "source_file": "refs/adversarial_depth/torchattacks/attacks/apgdt.py", "source_location": "L210", "weight": 1.0}, {"source": "apgdt_apgdt_forward", "target": "apgdt_apgdt_perturb", "relation": "calls", "confidence": "EXTRACTED", "source_file": "refs/adversarial_depth/torchattacks/attacks/apgdt.py", "source_location": "L62", "weight": 1.0}, {"source": "apgdt_apgdt_attack_single_run", "target": "apgdt_apgdt_dlr_loss_targeted", "relation": "calls", "confidence": "EXTRACTED", "source_file": "refs/adversarial_depth/torchattacks/attacks/apgdt.py", "source_location": "L110", "weight": 1.0}, {"source": "apgdt_apgdt_attack_single_run", "target": "apgdt_apgdt_check_oscillation", "relation": "calls", "confidence": "EXTRACTED", "source_file": "refs/adversarial_depth/torchattacks/attacks/apgdt.py", "source_location": "L190", "weight": 1.0}, {"source": "apgdt_apgdt_perturb", "target": "apgdt_apgdt_attack_single_run", "relation": "calls", "confidence": "EXTRACTED", "source_file": "refs/adversarial_depth/torchattacks/attacks/apgdt.py", "source_location": "L237", "weight": 1.0}, {"source": "apgdt_rationale_11", "target": "apgdt_apgdt", "relation": "rationale_for", "confidence": "EXTRACTED", "source_file": "refs/adversarial_depth/torchattacks/attacks/apgdt.py", "source_location": "L11", "weight": 1.0}, {"source": "apgdt_rationale_57", "target": "apgdt_apgdt_forward", "relation": "rationale_for", "confidence": "EXTRACTED", "source_file": "refs/adversarial_depth/torchattacks/attacks/apgdt.py", "source_location": "L57", "weight": 1.0}]}