{"nodes": [{"id": "synthia", "label": "synthia.py", "file_type": "code", "source_file": "refs/mfuser/mmseg/datasets/synthia.py", "source_location": "L1"}, {"id": "synthia_synthiadataset", "label": "SynthiaDataset", "file_type": "code", "source_file": "refs/mfuser/mmseg/datasets/synthia.py", "source_location": "L7"}, {"id": "customdataset", "label": "CustomDataset", "file_type": "code", "source_file": "", "source_location": ""}, {"id": "synthia_synthiadataset_init", "label": ".__init__()", "file_type": "code", "source_file": "refs/mfuser/mmseg/datasets/synthia.py", "source_location": "L11"}], "edges": [{"source": "synthia", "target": "", "relation": "imports_from", "confidence": "EXTRACTED", "source_file": "refs/mfuser/mmseg/datasets/synthia.py", "source_location": "L1", "weight": 1.0}, {"source": "synthia", "target": "builder", "relation": "imports_from", "confidence": "EXTRACTED", "source_file": "refs/mfuser/mmseg/datasets/synthia.py", "source_location": "L2", "weight": 1.0}, {"source": "synthia", "target": "custom", "relation": "imports_from", "confidence": "EXTRACTED", "source_file": "refs/mfuser/mmseg/datasets/synthia.py", "source_location": "L3", "weight": 1.0}, {"source": "synthia", "target": "synthia_synthiadataset", "relation": "contains", "confidence": "EXTRACTED", "source_file": "refs/mfuser/mmseg/datasets/synthia.py", "source_location": "L7", "weight": 1.0}, {"source": "synthia_synthiadataset", "target": "customdataset", "relation": "inherits", "confidence": "EXTRACTED", "source_file": "refs/mfuser/mmseg/datasets/synthia.py", "source_location": "L7", "weight": 1.0}, {"source": "synthia_synthiadataset", "target": "synthia_synthiadataset_init", "relation": "method", "confidence": "EXTRACTED", "source_file": "refs/mfuser/mmseg/datasets/synthia.py", "source_location": "L11", "weight": 1.0}]}