{"nodes": [{"id": "inference", "label": "inference.py", "file_type": "code", "source_file": "refs/dinov3/dinov3/eval/segmentation/inference.py", "source_location": "L1"}, {"id": "inference_make_inference", "label": "make_inference()", "file_type": "code", "source_file": "refs/dinov3/dinov3/eval/segmentation/inference.py", "source_location": "L14"}, {"id": "inference_slide_inference", "label": "slide_inference()", "file_type": "code", "source_file": "refs/dinov3/dinov3/eval/segmentation/inference.py", "source_location": "L93"}, {"id": "inference_rationale_27", "label": "Make inference on a given image, and reverts horizontal flip TTA if applicable.", "file_type": "rationale", "source_file": "refs/dinov3/dinov3/eval/segmentation/inference.py", "source_location": "L27"}, {"id": "inference_rationale_102", "label": "Inference by sliding-window with overlap.     If h_crop > h_img or w_crop > w_im", "file_type": "rationale", "source_file": "refs/dinov3/dinov3/eval/segmentation/inference.py", "source_location": "L102"}], "edges": [{"source": "inference", "target": "typing", "relation": "imports_from", "confidence": "EXTRACTED", "source_file": "refs/dinov3/dinov3/eval/segmentation/inference.py", "source_location": "L6", "weight": 1.0}, {"source": "inference", "target": "torch", "relation": "imports", "confidence": "EXTRACTED", "source_file": "refs/dinov3/dinov3/eval/segmentation/inference.py", "source_location": "L8", "weight": 1.0}, {"source": "inference", "target": "torch_nn_functional", "relation": "imports", "confidence": "EXTRACTED", "source_file": "refs/dinov3/dinov3/eval/segmentation/inference.py", "source_location": "L9", "weight": 1.0}, {"source": "inference", "target": "torch", "relation": "imports_from", "confidence": "EXTRACTED", "source_file": "refs/dinov3/dinov3/eval/segmentation/inference.py", "source_location": "L10", "weight": 1.0}, {"source": "inference", "target": "torchvision_transforms", "relation": "imports_from", "confidence": "EXTRACTED", "source_file": "refs/dinov3/dinov3/eval/segmentation/inference.py", "source_location": "L11", "weight": 1.0}, {"source": "inference", "target": "inference_make_inference", "relation": "contains", "confidence": "EXTRACTED", "source_file": "refs/dinov3/dinov3/eval/segmentation/inference.py", "source_location": "L14", "weight": 1.0}, {"source": "inference", "target": "inference_slide_inference", "relation": "contains", "confidence": "EXTRACTED", "source_file": "refs/dinov3/dinov3/eval/segmentation/inference.py", "source_location": "L93", "weight": 1.0}, {"source": "inference_make_inference", "target": "inference_slide_inference", "relation": "calls", "confidence": "EXTRACTED", "source_file": "refs/dinov3/dinov3/eval/segmentation/inference.py", "source_location": "L58", "weight": 1.0}, {"source": "inference_rationale_27", "target": "inference_make_inference", "relation": "rationale_for", "confidence": "EXTRACTED", "source_file": "refs/dinov3/dinov3/eval/segmentation/inference.py", "source_location": "L27", "weight": 1.0}, {"source": "inference_rationale_102", "target": "inference_slide_inference", "relation": "rationale_for", "confidence": "EXTRACTED", "source_file": "refs/dinov3/dinov3/eval/segmentation/inference.py", "source_location": "L102", "weight": 1.0}]}