{"nodes": [{"id": "geometry", "label": "geometry.py", "file_type": "code", "source_file": "refs/zoedepth/zoedepth/utils/geometry.py", "source_location": "L1"}, {"id": "geometry_get_intrinsics", "label": "get_intrinsics()", "file_type": "code", "source_file": "refs/zoedepth/zoedepth/utils/geometry.py", "source_location": "L27"}, {"id": "geometry_depth_to_points", "label": "depth_to_points()", "file_type": "code", "source_file": "refs/zoedepth/zoedepth/utils/geometry.py", "source_location": "L39"}, {"id": "geometry_create_triangles", "label": "create_triangles()", "file_type": "code", "source_file": "refs/zoedepth/zoedepth/utils/geometry.py", "source_location": "L75"}, {"id": "geometry_rationale_28", "label": "Intrinsics for a pinhole camera model.     Assume fov of 55 degrees and central", "file_type": "rationale", "source_file": "refs/zoedepth/zoedepth/utils/geometry.py", "source_location": "L28"}, {"id": "geometry_rationale_76", "label": "Reference: https://github.com/google-research/google-research/blob/e96197de06613", "file_type": "rationale", "source_file": "refs/zoedepth/zoedepth/utils/geometry.py", "source_location": "L76"}], "edges": [{"source": "geometry", "target": "numpy", "relation": "imports", "confidence": "EXTRACTED", "source_file": "refs/zoedepth/zoedepth/utils/geometry.py", "source_location": "L25", "weight": 1.0}, {"source": "geometry", "target": "geometry_get_intrinsics", "relation": "contains", "confidence": "EXTRACTED", "source_file": "refs/zoedepth/zoedepth/utils/geometry.py", "source_location": "L27", "weight": 1.0}, {"source": "geometry", "target": "geometry_depth_to_points", "relation": "contains", "confidence": "EXTRACTED", "source_file": "refs/zoedepth/zoedepth/utils/geometry.py", "source_location": "L39", "weight": 1.0}, {"source": "geometry", "target": "geometry_create_triangles", "relation": "contains", "confidence": "EXTRACTED", "source_file": "refs/zoedepth/zoedepth/utils/geometry.py", "source_location": "L75", "weight": 1.0}, {"source": "geometry_depth_to_points", "target": "geometry_get_intrinsics", "relation": "calls", "confidence": "EXTRACTED", "source_file": "refs/zoedepth/zoedepth/utils/geometry.py", "source_location": "L41", "weight": 1.0}, {"source": "geometry_rationale_28", "target": "geometry_get_intrinsics", "relation": "rationale_for", "confidence": "EXTRACTED", "source_file": "refs/zoedepth/zoedepth/utils/geometry.py", "source_location": "L28", "weight": 1.0}, {"source": "geometry_rationale_76", "target": "geometry_create_triangles", "relation": "rationale_for", "confidence": "EXTRACTED", "source_file": "refs/zoedepth/zoedepth/utils/geometry.py", "source_location": "L76", "weight": 1.0}]}