{"nodes": [{"id": "gn", "label": "gn.py", "file_type": "code", "source_file": "refs/adversarial_depth/torchattacks/attacks/gn.py", "source_location": "L1"}, {"id": "gn_gn", "label": "GN", "file_type": "code", "source_file": "refs/adversarial_depth/torchattacks/attacks/gn.py", "source_location": "L6"}, {"id": "attack", "label": "Attack", "file_type": "code", "source_file": "", "source_location": ""}, {"id": "gn_gn_init", "label": ".__init__()", "file_type": "code", "source_file": "refs/adversarial_depth/torchattacks/attacks/gn.py", "source_location": "L24"}, {"id": "gn_gn_forward", "label": ".forward()", "file_type": "code", "source_file": "refs/adversarial_depth/torchattacks/attacks/gn.py", "source_location": "L29"}, {"id": "gn_rationale_7", "label": "r\"\"\"     Add Gaussian Noise.      Arguments:         model (nn.Module): model to", "file_type": "rationale", "source_file": "refs/adversarial_depth/torchattacks/attacks/gn.py", "source_location": "L7"}, {"id": "gn_rationale_30", "label": "r\"\"\"         Overridden.", "file_type": "rationale", "source_file": "refs/adversarial_depth/torchattacks/attacks/gn.py", "source_location": "L30"}], "edges": [{"source": "gn", "target": "torch", "relation": "imports", "confidence": "EXTRACTED", "source_file": "refs/adversarial_depth/torchattacks/attacks/gn.py", "source_location": "L1", "weight": 1.0}, {"source": "gn", "target": "attack", "relation": "imports_from", "confidence": "EXTRACTED", "source_file": "refs/adversarial_depth/torchattacks/attacks/gn.py", "source_location": "L3", "weight": 1.0}, {"source": "gn", "target": "gn_gn", "relation": "contains", "confidence": "EXTRACTED", "source_file": "refs/adversarial_depth/torchattacks/attacks/gn.py", "source_location": "L6", "weight": 1.0}, {"source": "gn_gn", "target": "attack", "relation": "inherits", "confidence": "EXTRACTED", "source_file": "refs/adversarial_depth/torchattacks/attacks/gn.py", "source_location": "L6", "weight": 1.0}, {"source": "gn_gn", "target": "gn_gn_init", "relation": "method", "confidence": "EXTRACTED", "source_file": "refs/adversarial_depth/torchattacks/attacks/gn.py", "source_location": "L24", "weight": 1.0}, {"source": "gn_gn", "target": "gn_gn_forward", "relation": "method", "confidence": "EXTRACTED", "source_file": "refs/adversarial_depth/torchattacks/attacks/gn.py", "source_location": "L29", "weight": 1.0}, {"source": "gn_rationale_7", "target": "gn_gn", "relation": "rationale_for", "confidence": "EXTRACTED", "source_file": "refs/adversarial_depth/torchattacks/attacks/gn.py", "source_location": "L7", "weight": 1.0}, {"source": "gn_rationale_30", "target": "gn_gn_forward", "relation": "rationale_for", "confidence": "EXTRACTED", "source_file": "refs/adversarial_depth/torchattacks/attacks/gn.py", "source_location": "L30", "weight": 1.0}]}