{"nodes": [{"id": "depth_cache", "label": "depth_cache.py", "file_type": "code", "source_file": "mbps/data/depth_cache.py", "source_location": "L1"}, {"id": "depth_cache_depthcache", "label": "DepthCache", "file_type": "code", "source_file": "mbps/data/depth_cache.py", "source_location": "L16"}, {"id": "depth_cache_depthcache_init", "label": ".__init__()", "file_type": "code", "source_file": "mbps/data/depth_cache.py", "source_location": "L25"}, {"id": "depth_cache_depthcache_load", "label": ".load()", "file_type": "code", "source_file": "mbps/data/depth_cache.py", "source_location": "L41"}, {"id": "depth_cache_depthcache_normalize_depth", "label": "._normalize_depth()", "file_type": "code", "source_file": "mbps/data/depth_cache.py", "source_location": "L76"}, {"id": "depth_cache_depthcache_compute_dataset_stats", "label": ".compute_dataset_stats()", "file_type": "code", "source_file": "mbps/data/depth_cache.py", "source_location": "L96"}, {"id": "depth_cache_get_depth_cache", "label": "get_depth_cache()", "file_type": "code", "source_file": "mbps/data/depth_cache.py", "source_location": "L135"}, {"id": "depth_cache_rationale_1", "label": "ZoeDepth cache utilities for loading pre-computed depth maps.  Handles loading,", "file_type": "rationale", "source_file": "mbps/data/depth_cache.py", "source_location": "L1"}, {"id": "depth_cache_rationale_17", "label": "Cache for pre-computed ZoeDepth predictions.      Args:         cache_dir: Direc", "file_type": "rationale", "source_file": "mbps/data/depth_cache.py", "source_location": "L17"}, {"id": "depth_cache_rationale_42", "label": "Load a depth map from cache.          Args:             image_id: Image identifi", "file_type": "rationale", "source_file": "mbps/data/depth_cache.py", "source_location": "L42"}, {"id": "depth_cache_rationale_77", "label": "Normalize depth to [0, 1] range.          Args:             depth: Raw depth val", "file_type": "rationale", "source_file": "mbps/data/depth_cache.py", "source_location": "L77"}, {"id": "depth_cache_rationale_99", "label": "Compute global min/max depth across a dataset.          Args:             image_", "file_type": "rationale", "source_file": "mbps/data/depth_cache.py", "source_location": "L99"}, {"id": "depth_cache_rationale_140", "label": "Create a DepthCache with dataset-specific normalization.      Args:         data", "file_type": "rationale", "source_file": "mbps/data/depth_cache.py", "source_location": "L140"}], "edges": [{"source": "depth_cache", "target": "os", "relation": "imports", "confidence": "EXTRACTED", "source_file": "mbps/data/depth_cache.py", "source_location": "L9", "weight": 1.0}, {"source": "depth_cache", "target": "typing", "relation": "imports_from", "confidence": "EXTRACTED", "source_file": "mbps/data/depth_cache.py", "source_location": "L10", "weight": 1.0}, {"source": "depth_cache", "target": "numpy", "relation": "imports", "confidence": "EXTRACTED", "source_file": "mbps/data/depth_cache.py", "source_location": "L12", "weight": 1.0}, {"source": "depth_cache", "target": "absl", "relation": "imports_from", "confidence": "EXTRACTED", "source_file": "mbps/data/depth_cache.py", "source_location": "L13", "weight": 1.0}, {"source": "depth_cache", "target": "depth_cache_depthcache", "relation": "contains", "confidence": "EXTRACTED", "source_file": "mbps/data/depth_cache.py", "source_location": "L16", "weight": 1.0}, {"source": "depth_cache_depthcache", "target": "depth_cache_depthcache_init", "relation": "method", "confidence": "EXTRACTED", "source_file": "mbps/data/depth_cache.py", "source_location": "L25", "weight": 1.0}, {"source": "depth_cache_depthcache", "target": "depth_cache_depthcache_load", "relation": "method", "confidence": "EXTRACTED", "source_file": "mbps/data/depth_cache.py", "source_location": "L41", "weight": 1.0}, {"source": "depth_cache_depthcache", "target": "depth_cache_depthcache_normalize_depth", "relation": "method", "confidence": "EXTRACTED", "source_file": "mbps/data/depth_cache.py", "source_location": "L76", "weight": 1.0}, {"source": "depth_cache_depthcache", "target": "depth_cache_depthcache_compute_dataset_stats", "relation": "method", "confidence": "EXTRACTED", "source_file": "mbps/data/depth_cache.py", "source_location": "L96", "weight": 1.0}, {"source": "depth_cache", "target": "depth_cache_get_depth_cache", "relation": "contains", "confidence": "EXTRACTED", "source_file": "mbps/data/depth_cache.py", "source_location": "L135", "weight": 1.0}, {"source": "depth_cache_depthcache_load", "target": "depth_cache_depthcache_normalize_depth", "relation": "calls", "confidence": "EXTRACTED", "source_file": "mbps/data/depth_cache.py", "source_location": "L72", "weight": 1.0}, {"source": "depth_cache_depthcache_compute_dataset_stats", "target": "depth_cache_depthcache_load", "relation": "calls", "confidence": "EXTRACTED", "source_file": "mbps/data/depth_cache.py", "source_location": "L114", "weight": 1.0}, {"source": "depth_cache_get_depth_cache", "target": "depth_cache_depthcache", "relation": "calls", "confidence": "EXTRACTED", "source_file": "mbps/data/depth_cache.py", "source_location": "L151", "weight": 1.0}, {"source": "depth_cache_rationale_1", "target": "depth_cache", "relation": "rationale_for", "confidence": "EXTRACTED", "source_file": "mbps/data/depth_cache.py", "source_location": "L1", "weight": 1.0}, {"source": "depth_cache_rationale_17", "target": "depth_cache_depthcache", "relation": "rationale_for", "confidence": "EXTRACTED", "source_file": "mbps/data/depth_cache.py", "source_location": "L17", "weight": 1.0}, {"source": "depth_cache_rationale_42", "target": "depth_cache_depthcache_load", "relation": "rationale_for", "confidence": "EXTRACTED", "source_file": "mbps/data/depth_cache.py", "source_location": "L42", "weight": 1.0}, {"source": "depth_cache_rationale_77", "target": "depth_cache_depthcache_normalize_depth", "relation": "rationale_for", "confidence": "EXTRACTED", "source_file": "mbps/data/depth_cache.py", "source_location": "L77", "weight": 1.0}, {"source": "depth_cache_rationale_99", "target": "depth_cache_depthcache_compute_dataset_stats", "relation": "rationale_for", "confidence": "EXTRACTED", "source_file": "mbps/data/depth_cache.py", "source_location": "L99", "weight": 1.0}, {"source": "depth_cache_rationale_140", "target": "depth_cache_get_depth_cache", "relation": "rationale_for", "confidence": "EXTRACTED", "source_file": "mbps/data/depth_cache.py", "source_location": "L140", "weight": 1.0}]}